counter_project/counter.v
module counter4bit(
input clk,
input reset,
output reg [3:0] count
);

always @(posedge clk or posedge reset) begin
    if (reset)
        count <= 4'b0000;
    else
        count <= count - 1;
end

endmodule

counter_project/tb.v
module tb;

reg clk;
reg reset;
wire [3:0] count;

counter4bit uut(clk, reset, count);

initial begin
$dumpfile("dump.vcd");
$dumpvars(0,tb);

clk = 0;
reset = 1;

#5 reset = 0;

#100 $finish;
end

always #5 clk = ~clk;

endmodule

counter_project/dump.vcd
$date
	Mon Apr 20 20:01:08 2026
$end
$version
	Icarus Verilog
$end
$timescale
	1s
$end
$scope module tb $end
$var wire 4 ! count [3:0] $end
$var reg 1 " clk $end
$var reg 1 # reset $end
$scope module uut $end
$var wire 1 " clk $end
$var wire 1 # reset $end
$var reg 4 $ count [3:0] $end
$upscope $end
$upscope $end
$enddefinitions $end
#0
$dumpvars
b0 $
1#
0"
b0 !
$end
#5
b1111 !
b1111 $
1"
0#
#10
0"
#15
b1110 !
b1110 $
1"
#20
0"
#25
b1101 !
b1101 $
1"
#30
0"
#35
b1100 !
b1100 $
1"
#40
0"
#45
b1011 !
b1011 $
1"
#50
0"
#55
b1010 !
b1010 $
1"
#60
0"
#65
b1001 !
b1001 $
1"
#70
0"
#75
b1000 !
b1000 $
1"
#80
0"
#85
b111 !
b111 $
1"
#90
0"
#95
b110 !
b110 $
1"
#100
0"
#105
b101 !
b101 $
1"
