ALU_Project/alu.v
module alu4bit(
input [3:0] A,
input [3:0] B,
input [2:0] SEL,
output reg [3:0] Y
);

always @(*) begin
case(SEL)
3'b000: Y = A + B;
3'b001: Y = A - B;
3'b010: Y = A & B;
3'b011: Y = A | B;
3'b100: Y = A ^ B;
3'b101: Y = ~A;
3'b110: Y = A << 1;
3'b111: Y = A >> 1;
endcase
end

endmodule

ALU_Project/tb.v
module tb;

reg [3:0] A,B;
reg [2:0] SEL;
wire [3:0] Y;

alu4bit uut(A,B,SEL,Y);

initial begin
$dumpfile("dump.vcd");
$dumpvars(0,tb);

A = 4'b1001;
B = 4'b0011;

SEL = 3'b000; #10;
SEL = 3'b001; #10;
SEL = 3'b010; #10;
SEL = 3'b011; #10;
SEL = 3'b100; #10;
SEL = 3'b101; #10;
SEL = 3'b110; #10;
SEL = 3'b111; #10;

$finish;
end

endmodule

ALU_Project/dump.vcd
$date
	Mon Apr 20 17:19:51 2026
$end
$version
	Icarus Verilog
$end
$timescale
	1s
$end
$scope module tb $end
$var wire 4 ! Y [3:0] $end
$var reg 4 " A [3:0] $end
$var reg 4 # B [3:0] $end
$var reg 3 $ SEL [2:0] $end
$scope module uut $end
$var wire 4 % A [3:0] $end
$var wire 4 & B [3:0] $end
$var wire 3 ' SEL [2:0] $end
$var reg 4 ( Y [3:0] $end
$upscope $end
$upscope $end
$enddefinitions $end
#0
$dumpvars
b1100 (
b0 '
b11 &
b1001 %
b0 $
b11 #
b1001 "
b1100 !
$end
#10
b110 !
b110 (
b1 $
b1 '
#20
b1 !
b1 (
b10 $
b10 '
#30
b1011 !
b1011 (
b11 $
b11 '
#40
b1010 !
b1010 (
b100 $
b100 '
#50
b110 !
b110 (
b101 $
b101 '
#60
b10 !
b10 (
b110 $
b110 '
#70
b100 !
b100 (
b111 $
b111 '
