Shiftregister project/shift.v
module shift (
    input wire clk,
    input wire reset,
    input wire load,
    input wire [3:0] data_in,
    output reg [3:0] q
);

always @(posedge clk or posedge reset) begin
    if (reset)
        q <= 4'b0000;

    else if (load)
        q <= data_in;

    else
        q <= q >> 1;   // Right Shift
end

endmodule

Shiftregister project/tb.v
module tb;

reg clk;
reg reset;
reg load;
reg [3:0] data_in;
wire [3:0] q;

shift dut (
    .clk(clk),
    .reset(reset),
    .load(load),
    .data_in(data_in),
    .q(q)
);

initial clk = 0;
always #5 clk = ~clk;

initial begin
    $dumpfile("dump.vcd");
    $dumpvars(0, tb);

    reset = 1;
    load = 0;
    data_in = 4'b0000;

    #10 reset = 0;

    // Load data
    #10 load = 1;
        data_in = 4'b1101;

    #10 load = 0;

    // Observe shifting
    #50 $finish;
end

initial begin
    $monitor("Time=%0t | clk=%b reset=%b load=%b data_in=%b q=%b",
              $time, clk, reset, load, data_in, q);
end

endmodule

Shiftregister project/dump.vcd
$date
	Fri Apr 24 16:51:26 2026
$end
$version
	Icarus Verilog
$end
$timescale
	1s
$end
$scope module tb $end
$var wire 4 ! q [3:0] $end
$var reg 1 " clk $end
$var reg 4 # data_in [3:0] $end
$var reg 1 $ load $end
$var reg 1 % reset $end
$scope module dut $end
$var wire 1 " clk $end
$var wire 4 & data_in [3:0] $end
$var wire 1 $ load $end
$var wire 1 % reset $end
$var reg 4 ' q [3:0] $end
$upscope $end
$upscope $end
$enddefinitions $end
#0
$dumpvars
b0 '
b0 &
1%
0$
b0 #
0"
b0 !
$end
#5
1"
#10
0"
0%
#15
1"
#20
0"
b1101 #
b1101 &
1$
#25
b1101 !
b1101 '
1"
#30
0"
0$
#35
b110 !
b110 '
1"
#40
0"
#45
b11 !
b11 '
1"
#50
0"
#55
b1 !
b1 '
1"
#60
0"
#65
b0 !
b0 '
1"
