4bit UART/uart.v
module uart (
    input wire clk,
    input wire reset,
    input wire start,
    input wire [3:0] data_in,
    output reg tx,
    output reg busy
);

reg [1:0] state;
reg [2:0] bit_count;
reg [3:0] data_reg;

parameter IDLE  = 2'b00,
          START = 2'b01,
          DATA  = 2'b10,
          STOP  = 2'b11;

always @(posedge clk or posedge reset) begin
    if(reset) begin
        state <= IDLE;
        tx <= 1;
        busy <= 0;
        bit_count <= 0;
        data_reg <= 0;
    end
    else begin
        case(state)

        IDLE: begin
            tx <= 1;
            busy <= 0;
            if(start) begin
                data_reg <= data_in;
                state <= START;
                busy <= 1;
            end
        end

        START: begin
            tx <= 0;
            bit_count <= 0;
            state <= DATA;
        end

        DATA: begin
            tx <= data_reg[0];
            data_reg <= data_reg >> 1;

            if(bit_count == 3)
                state <= STOP;
            else
                bit_count <= bit_count + 1;
        end

        STOP: begin
            tx <= 1;
            state <= IDLE;
            busy <= 0;
        end

        endcase
    end
end

endmodule

4bit UART/tb.v
module tb;

reg clk;
reg reset;
reg start;
reg [3:0] data_in;
wire tx;
wire busy;

uart dut (
    .clk(clk),
    .reset(reset),
    .start(start),
    .data_in(data_in),
    .tx(tx),
    .busy(busy)
);

initial clk = 0;
always #5 clk = ~clk;

initial begin
    $dumpfile("dump.vcd");
    $dumpvars(0,tb);

    reset = 1;
    start = 0;
    data_in = 4'b1011;

    #10 reset = 0;
    #10 start = 1;
    #10 start = 0;

    #100 $finish;
end

endmodule

4bit UART/dump.vcd
$date
	Mon Apr 27 17:54:22 2026
$end
$version
	Icarus Verilog
$end
$timescale
	1s
$end
$scope module tb $end
$var wire 1 ! tx $end
$var wire 1 " busy $end
$var reg 1 # clk $end
$var reg 4 $ data_in [3:0] $end
$var reg 1 % reset $end
$var reg 1 & start $end
$scope module dut $end
$var wire 1 # clk $end
$var wire 4 ' data_in [3:0] $end
$var wire 1 % reset $end
$var wire 1 & start $end
$var reg 3 ( bit_count [2:0] $end
$var reg 1 " busy $end
$var reg 4 ) data_reg [3:0] $end
$var reg 2 * state [1:0] $end
$var reg 1 ! tx $end
$upscope $end
$upscope $end
$enddefinitions $end
#0
$dumpvars
b0 *
b0 )
b0 (
b1011 '
0&
1%
b1011 $
0#
0"
1!
$end
#5
1#
#10
0#
0%
#15
1#
#20
0#
1&
#25
1"
b1 *
b1011 )
1#
#30
0#
0&
#35
b10 *
0!
1#
#40
0#
#45
b1 (
b101 )
1!
1#
#50
0#
#55
b10 (
b10 )
1#
#60
0#
#65
b11 (
b1 )
0!
1#
#70
0#
#75
b11 *
b0 )
1!
1#
#80
0#
#85
0"
b0 *
1#
